langgraph_dynamodb_saver/LICENSE
langgraph_dynamodb_saver/__init__.py
langgraph_dynamodb_saver/dynamodbSaver.py
langgraph_dynamodb_saver-0.2.1.dist-info/METADATA
langgraph_dynamodb_saver-0.2.1.dist-info/WHEEL
langgraph_dynamodb_saver-0.2.1.dist-info/RECORD
